MANIFEST.in
README
setup.py
test/test.py
zijin/__init__.py
zijin/data.csv
zijin/zijin_basic.py
zijin/zijin_config.py
zijin/zijin_data.py
zijin/zijin_functions.py
zijin/zijin_log.py
zijin/zijin_objects.py
zijin/zijin_util.py
zijin.egg-info/PKG-INFO
zijin.egg-info/SOURCES.txt
zijin.egg-info/dependency_links.txt
zijin.egg-info/not-zip-safe
zijin.egg-info/requires.txt
zijin.egg-info/top_level.txt