Metadata-Version: 1.0
Name: zijin
Version: 1.6
Summary: zijin test package
Home-page: https://github.com/xxh13/zijin_.git
Author: xxh13
Author-email: 15850781776@163.com
License: MIT
Platform: UNKNOWN
